Compiled from "TileEntityWaterTrap.java"
public class com.pam.harvestcraft.tileentities.TileEntityWaterTrap extends net.minecraft.tileentity.TileEntity implements net.minecraft.util.ITickable {
  public int runTime;

  public int currentBeeRunTime;

  public int produceTime;

  public com.pam.harvestcraft.tileentities.TileEntityWaterTrap();
    Code:
       0: aload_0
       1: invokespecial #17                 // Method net/minecraft/tileentity/TileEntity."<init>":()V
       4: aload_0
       5: new           #19                 // class net/minecraftforge/items/ItemStackHandler
       8: dup
       9: bipush        19
      11: invokespecial #22                 // Method net/minecraftforge/items/ItemStackHandler."<init>":(I)V
      14: putfield      #24                 // Field itemstackhandler:Lnet/minecraftforge/items/ItemStackHandler;
      17: aload_0
      18: iconst_0
      19: putfield      #26                 // Field runTime:I
      22: aload_0
      23: iconst_0
      24: putfield      #28                 // Field currentBeeRunTime:I
      27: aload_0
      28: iconst_0
      29: putfield      #30                 // Field produceTime:I
      32: return

  public boolean hasCapability(net.minecraftforge.common.capabilities.Capability<?>, net.minecraft.util.EnumFacing);
    Code:
       0: aload_1
       1: getstatic     #40                 // Field net/minecraftforge/items/CapabilityItemHandler.ITEM_HANDLER_CAPABILITY:Lnet/minecraftforge/common/capabilities/Capability;
       4: if_acmpeq     16
       7: aload_0
       8: aload_1
       9: aload_2
      10: invokespecial #42                 // Method net/minecraft/tileentity/TileEntity.hasCapability:(Lnet/minecraftforge/common/capabilities/Capability;Lnet/minecraft/util/EnumFacing;)Z
      13: ifeq          20
      16: iconst_1
      17: goto          21
      20: iconst_0
      21: ireturn

  public <T> T getCapability(net.minecraftforge.common.capabilities.Capability<T>, net.minecraft.util.EnumFacing);
    Code:
       0: aload_1
       1: getstatic     #40                 // Field net/minecraftforge/items/CapabilityItemHandler.ITEM_HANDLER_CAPABILITY:Lnet/minecraftforge/common/capabilities/Capability;
       4: if_acmpne     18
       7: getstatic     #40                 // Field net/minecraftforge/items/CapabilityItemHandler.ITEM_HANDLER_CAPABILITY:Lnet/minecraftforge/common/capabilities/Capability;
      10: aload_0
      11: getfield      #24                 // Field itemstackhandler:Lnet/minecraftforge/items/ItemStackHandler;
      14: invokevirtual #54                 // Method net/minecraftforge/common/capabilities/Capability.cast:(Ljava/lang/Object;)Ljava/lang/Object;
      17: areturn
      18: aload_0
      19: aload_1
      20: aload_2
      21: invokespecial #56                 // Method net/minecraft/tileentity/TileEntity.getCapability:(Lnet/minecraftforge/common/capabilities/Capability;Lnet/minecraft/util/EnumFacing;)Ljava/lang/Object;
      24: areturn

  public void readFromNBT(net.minecraft.nbt.NBTTagCompound);
    Code:
       0: aload_0
       1: aload_1
       2: invokespecial #61                 // Method net/minecraft/tileentity/TileEntity.readFromNBT:(Lnet/minecraft/nbt/NBTTagCompound;)V
       5: aload_0
       6: getfield      #24                 // Field itemstackhandler:Lnet/minecraftforge/items/ItemStackHandler;
       9: aload_1
      10: ldc           #63                 // String Items
      12: invokevirtual #69                 // Method net/minecraft/nbt/NBTTagCompound.getTag:(Ljava/lang/String;)Lnet/minecraft/nbt/NBTBase;
      15: checkcast     #65                 // class net/minecraft/nbt/NBTTagCompound
      18: invokevirtual #72                 // Method net/minecraftforge/items/ItemStackHandler.deserializeNBT:(Lnet/minecraft/nbt/NBTTagCompound;)V
      21: aload_0
      22: aload_1
      23: ldc           #74                 // String RunTime
      25: invokevirtual #78                 // Method net/minecraft/nbt/NBTTagCompound.getShort:(Ljava/lang/String;)S
      28: putfield      #26                 // Field runTime:I
      31: aload_0
      32: aload_1
      33: ldc           #80                 // String ProduceTime
      35: invokevirtual #78                 // Method net/minecraft/nbt/NBTTagCompound.getShort:(Ljava/lang/String;)S
      38: putfield      #30                 // Field produceTime:I
      41: aload_0
      42: aload_0
      43: aload_0
      44: getfield      #24                 // Field itemstackhandler:Lnet/minecraftforge/items/ItemStackHandler;
      47: iconst_1
      48: invokevirtual #84                 // Method net/minecraftforge/items/ItemStackHandler.getStackInSlot:(I)Lnet/minecraft/item/ItemStack;
      51: invokespecial #88                 // Method getRunTime:(Lnet/minecraft/item/ItemStack;)I
      54: putfield      #28                 // Field currentBeeRunTime:I
      57: return

  public net.minecraft.nbt.NBTTagCompound writeToNBT(net.minecraft.nbt.NBTTagCompound);
    Code:
       0: aload_1
       1: ldc           #74                 // String RunTime
       3: aload_0
       4: getfield      #26                 // Field runTime:I
       7: i2s
       8: invokevirtual #97                 // Method net/minecraft/nbt/NBTTagCompound.setShort:(Ljava/lang/String;S)V
      11: aload_1
      12: ldc           #80                 // String ProduceTime
      14: aload_0
      15: getfield      #30                 // Field produceTime:I
      18: i2s
      19: invokevirtual #97                 // Method net/minecraft/nbt/NBTTagCompound.setShort:(Ljava/lang/String;S)V
      22: aload_1
      23: ldc           #63                 // String Items
      25: aload_0
      26: getfield      #24                 // Field itemstackhandler:Lnet/minecraftforge/items/ItemStackHandler;
      29: invokevirtual #101                // Method net/minecraftforge/items/ItemStackHandler.serializeNBT:()Lnet/minecraft/nbt/NBTTagCompound;
      32: invokevirtual #105                // Method net/minecraft/nbt/NBTTagCompound.setTag:(Ljava/lang/String;Lnet/minecraft/nbt/NBTBase;)V
      35: aload_0
      36: aload_1
      37: invokespecial #107                // Method net/minecraft/tileentity/TileEntity.writeToNBT:(Lnet/minecraft/nbt/NBTTagCompound;)Lnet/minecraft/nbt/NBTTagCompound;
      40: areturn

  public int countFlowers();
    Code:
       0: iconst_2
       1: istore_1
       2: iconst_0
       3: istore_2
       4: aload_0
       5: getfield      #113                // Field pos:Lnet/minecraft/util/math/BlockPos;
       8: invokevirtual #118                // Method net/minecraft/util/math/BlockPos.getX:()I
      11: istore_3
      12: aload_0
      13: getfield      #113                // Field pos:Lnet/minecraft/util/math/BlockPos;
      16: invokevirtual #121                // Method net/minecraft/util/math/BlockPos.getY:()I
      19: istore        4
      21: aload_0
      22: getfield      #113                // Field pos:Lnet/minecraft/util/math/BlockPos;
      25: invokevirtual #124                // Method net/minecraft/util/math/BlockPos.getZ:()I
      28: istore        5
      30: iload_1
      31: ineg
      32: istore        6
      34: iload         6
      36: iload_1
      37: if_icmpgt     202
      40: iload_1
      41: ineg
      42: istore        7
      44: iload         7
      46: iload_1
      47: if_icmpgt     196
      50: iload         6
      52: iload         6
      54: imul
      55: iload         7
      57: iload         7
      59: imul
      60: iadd
      61: iload_1
      62: iload_1
      63: imul
      64: if_icmpgt     190
      67: iload         6
      69: iload_1
      70: iconst_1
      71: isub
      72: ineg
      73: if_icmpne     85
      76: iload         7
      78: iload_1
      79: iconst_1
      80: isub
      81: ineg
      82: if_icmpeq     190
      85: iload         6
      87: iload_1
      88: iconst_1
      89: isub
      90: if_icmpne     101
      93: iload         7
      95: iload_1
      96: iconst_1
      97: isub
      98: if_icmpeq     190
     101: iload         6
     103: iload_1
     104: iconst_1
     105: isub
     106: if_icmpne     118
     109: iload         7
     111: iload_1
     112: iconst_1
     113: isub
     114: ineg
     115: if_icmpeq     190
     118: iload         6
     120: iload_1
     121: iconst_1
     122: isub
     123: ineg
     124: if_icmpne     135
     127: iload         7
     129: iload_1
     130: iconst_1
     131: isub
     132: if_icmpeq     190
     135: new           #115                // class net/minecraft/util/math/BlockPos
     138: dup
     139: iload_3
     140: iload         6
     142: iadd
     143: iload         4
     145: iload         5
     147: iload         7
     149: iadd
     150: invokespecial #127                // Method net/minecraft/util/math/BlockPos."<init>":(III)V
     153: astore        8
     155: aload_0
     156: getfield      #131                // Field world:Lnet/minecraft/world/World;
     159: aload         8
     161: invokevirtual #137                // Method net/minecraft/world/World.isBlockLoaded:(Lnet/minecraft/util/math/BlockPos;)Z
     164: ifeq          190
     167: aload_0
     168: getfield      #131                // Field world:Lnet/minecraft/world/World;
     171: aload         8
     173: invokevirtual #141                // Method net/minecraft/world/World.getBlockState:(Lnet/minecraft/util/math/BlockPos;)Lnet/minecraft/block/state/IBlockState;
     176: invokeinterface #147,  1          // InterfaceMethod net/minecraft/block/state/IBlockState.getBlock:()Lnet/minecraft/block/Block;
     181: getstatic     #153                // Field net/minecraft/init/Blocks.WATER:Lnet/minecraft/block/BlockStaticLiquid;
     184: if_acmpne     190
     187: iinc          2, 1
     190: iinc          7, 1
     193: goto          44
     196: iinc          6, 1
     199: goto          34
     202: iload_2
     203: ireturn

  public void update();
    Code:
       0: aload_0
       1: getfield      #26                 // Field runTime:I
       4: ifle          11
       7: iconst_1
       8: goto          12
      11: iconst_0
      12: istore_1
      13: iconst_0
      14: istore_2
      15: iload_1
      16: ifeq          29
      19: aload_0
      20: dup
      21: getfield      #26                 // Field runTime:I
      24: iconst_1
      25: isub
      26: putfield      #26                 // Field runTime:I
      29: aload_0
      30: getfield      #24                 // Field itemstackhandler:Lnet/minecraftforge/items/ItemStackHandler;
      33: bipush        18
      35: invokevirtual #84                 // Method net/minecraftforge/items/ItemStackHandler.getStackInSlot:(I)Lnet/minecraft/item/ItemStack;
      38: astore_3
      39: aload_0
      40: getfield      #131                // Field world:Lnet/minecraft/world/World;
      43: getfield      #166                // Field net/minecraft/world/World.isRemote:Z
      46: ifne          169
      49: aload_0
      50: getfield      #26                 // Field runTime:I
      53: ifne          98
      56: aload_0
      57: invokespecial #170                // Method canRun:()Z
      60: ifeq          98
      63: aload_0
      64: aload_0
      65: aload_0
      66: aload_3
      67: invokespecial #88                 // Method getRunTime:(Lnet/minecraft/item/ItemStack;)I
      70: dup_x1
      71: putfield      #26                 // Field runTime:I
      74: putfield      #28                 // Field currentBeeRunTime:I
      77: aload_0
      78: getfield      #26                 // Field runTime:I
      81: ifle          98
      84: iconst_1
      85: istore_2
      86: aload_3
      87: invokevirtual #175                // Method net/minecraft/item/ItemStack.isEmpty:()Z
      90: ifne          98
      93: aload_3
      94: iconst_1
      95: invokevirtual #178                // Method net/minecraft/item/ItemStack.shrink:(I)V
      98: aload_0
      99: invokespecial #170                // Method canRun:()Z
     102: ifeq          146
     105: aload_0
     106: dup
     107: getfield      #30                 // Field produceTime:I
     110: iconst_1
     111: iadd
     112: putfield      #30                 // Field produceTime:I
     115: aload_0
     116: getfield      #30                 // Field produceTime:I
     119: i2d
     120: aload_0
     121: invokespecial #180                // Method getRunTime:()I
     124: i2d
     125: invokestatic  #186                // Method java/lang/Math.floor:(D)D
     128: dcmpl
     129: iflt          151
     132: aload_0
     133: iconst_0
     134: putfield      #30                 // Field produceTime:I
     137: aload_0
     138: invokevirtual #189                // Method run:()V
     141: iconst_1
     142: istore_2
     143: goto          151
     146: aload_0
     147: iconst_0
     148: putfield      #30                 // Field produceTime:I
     151: iload_1
     152: aload_0
     153: getfield      #26                 // Field runTime:I
     156: ifle          163
     159: iconst_1
     160: goto          164
     163: iconst_0
     164: if_icmpeq     169
     167: iconst_1
     168: istore_2
     169: iload_2
     170: ifeq          211
     173: aload_0
     174: invokevirtual #192                // Method markDirty:()V
     177: aload_0
     178: getfield      #131                // Field world:Lnet/minecraft/world/World;
     181: aload_0
     182: getfield      #113                // Field pos:Lnet/minecraft/util/math/BlockPos;
     185: aload_0
     186: getfield      #131                // Field world:Lnet/minecraft/world/World;
     189: aload_0
     190: invokevirtual #196                // Method getPos:()Lnet/minecraft/util/math/BlockPos;
     193: invokevirtual #141                // Method net/minecraft/world/World.getBlockState:(Lnet/minecraft/util/math/BlockPos;)Lnet/minecraft/block/state/IBlockState;
     196: aload_0
     197: getfield      #131                // Field world:Lnet/minecraft/world/World;
     200: aload_0
     201: invokevirtual #196                // Method getPos:()Lnet/minecraft/util/math/BlockPos;
     204: invokevirtual #141                // Method net/minecraft/world/World.getBlockState:(Lnet/minecraft/util/math/BlockPos;)Lnet/minecraft/block/state/IBlockState;
     207: iconst_3
     208: invokevirtual #200                // Method net/minecraft/world/World.notifyBlockUpdate:(Lnet/minecraft/util/math/BlockPos;Lnet/minecraft/block/state/IBlockState;Lnet/minecraft/block/state/IBlockState;I)V
     211: return

  public void run();
    Code:
       0: aload_0
       1: invokevirtual #220                // Method getComb:()Lnet/minecraft/item/ItemStack;
       4: astore_1
       5: iconst_0
       6: istore_2
       7: iload_2
       8: bipush        18
      10: if_icmpge     51
      13: aload_0
      14: getfield      #24                 // Field itemstackhandler:Lnet/minecraftforge/items/ItemStackHandler;
      17: iload_2
      18: invokevirtual #84                 // Method net/minecraftforge/items/ItemStackHandler.getStackInSlot:(I)Lnet/minecraft/item/ItemStack;
      21: invokevirtual #175                // Method net/minecraft/item/ItemStack.isEmpty:()Z
      24: ifne          30
      27: goto          45
      30: aload_0
      31: getfield      #24                 // Field itemstackhandler:Lnet/minecraftforge/items/ItemStackHandler;
      34: iload_2
      35: aload_1
      36: invokevirtual #223                // Method net/minecraft/item/ItemStack.copy:()Lnet/minecraft/item/ItemStack;
      39: invokevirtual #227                // Method net/minecraftforge/items/ItemStackHandler.setStackInSlot:(ILnet/minecraft/item/ItemStack;)V
      42: goto          51
      45: iinc          2, 1
      48: goto          7
      51: return

  public net.minecraft.item.ItemStack getComb();
    Code:
       0: new           #231                // class java/util/Random
       3: dup
       4: invokespecial #232                // Method java/util/Random."<init>":()V
       7: astore_1
       8: aload_0
       9: getfield      #24                 // Field itemstackhandler:Lnet/minecraftforge/items/ItemStackHandler;
      12: bipush        18
      14: invokevirtual #84                 // Method net/minecraftforge/items/ItemStackHandler.getStackInSlot:(I)Lnet/minecraft/item/ItemStack;
      17: invokevirtual #175                // Method net/minecraft/item/ItemStack.isEmpty:()Z
      20: ifne          588
      23: aload_1
      24: bipush        32
      26: invokevirtual #236                // Method java/util/Random.nextInt:(I)I
      29: istore_2
      30: iload_2
      31: tableswitch   { // 0 to 31
                     0: 172
                     1: 185
                     2: 198
                     3: 211
                     4: 224
                     5: 237
                     6: 250
                     7: 263
                     8: 276
                     9: 289
                    10: 302
                    11: 315
                    12: 328
                    13: 341
                    14: 354
                    15: 367
                    16: 380
                    17: 393
                    18: 406
                    19: 419
                    20: 432
                    21: 445
                    22: 458
                    23: 471
                    24: 484
                    25: 497
                    26: 510
                    27: 523
                    28: 536
                    29: 549
                    30: 562
                    31: 575
               default: 588
          }
     172: new           #172                // class net/minecraft/item/ItemStack
     175: dup
     176: getstatic     #241                // Field net/minecraft/init/Items.FISH:Lnet/minecraft/item/Item;
     179: iconst_1
     180: iconst_0
     181: invokespecial #244                // Method net/minecraft/item/ItemStack."<init>":(Lnet/minecraft/item/Item;II)V
     184: areturn
     185: new           #172                // class net/minecraft/item/ItemStack
     188: dup
     189: getstatic     #241                // Field net/minecraft/init/Items.FISH:Lnet/minecraft/item/Item;
     192: iconst_1
     193: iconst_1
     194: invokespecial #244                // Method net/minecraft/item/ItemStack."<init>":(Lnet/minecraft/item/Item;II)V
     197: areturn
     198: new           #172                // class net/minecraft/item/ItemStack
     201: dup
     202: getstatic     #241                // Field net/minecraft/init/Items.FISH:Lnet/minecraft/item/Item;
     205: iconst_1
     206: iconst_2
     207: invokespecial #244                // Method net/minecraft/item/ItemStack."<init>":(Lnet/minecraft/item/Item;II)V
     210: areturn
     211: new           #172                // class net/minecraft/item/ItemStack
     214: dup
     215: getstatic     #241                // Field net/minecraft/init/Items.FISH:Lnet/minecraft/item/Item;
     218: iconst_1
     219: iconst_3
     220: invokespecial #244                // Method net/minecraft/item/ItemStack."<init>":(Lnet/minecraft/item/Item;II)V
     223: areturn
     224: new           #172                // class net/minecraft/item/ItemStack
     227: dup
     228: getstatic     #247                // Field com/pam/harvestcraft/item/ItemRegistry.anchovyrawItem:Lnet/minecraft/item/Item;
     231: iconst_1
     232: iconst_0
     233: invokespecial #244                // Method net/minecraft/item/ItemStack."<init>":(Lnet/minecraft/item/Item;II)V
     236: areturn
     237: new           #172                // class net/minecraft/item/ItemStack
     240: dup
     241: getstatic     #250                // Field com/pam/harvestcraft/item/ItemRegistry.bassrawItem:Lnet/minecraft/item/Item;
     244: iconst_1
     245: iconst_0
     246: invokespecial #244                // Method net/minecraft/item/ItemStack."<init>":(Lnet/minecraft/item/Item;II)V
     249: areturn
     250: new           #172                // class net/minecraft/item/ItemStack
     253: dup
     254: getstatic     #253                // Field com/pam/harvestcraft/item/ItemRegistry.carprawItem:Lnet/minecraft/item/Item;
     257: iconst_1
     258: iconst_0
     259: invokespecial #244                // Method net/minecraft/item/ItemStack."<init>":(Lnet/minecraft/item/Item;II)V
     262: areturn
     263: new           #172                // class net/minecraft/item/ItemStack
     266: dup
     267: getstatic     #256                // Field com/pam/harvestcraft/item/ItemRegistry.catfishrawItem:Lnet/minecraft/item/Item;
     270: iconst_1
     271: iconst_0
     272: invokespecial #244                // Method net/minecraft/item/ItemStack."<init>":(Lnet/minecraft/item/Item;II)V
     275: areturn
     276: new           #172                // class net/minecraft/item/ItemStack
     279: dup
     280: getstatic     #259                // Field com/pam/harvestcraft/item/ItemRegistry.charrrawItem:Lnet/minecraft/item/Item;
     283: iconst_1
     284: iconst_0
     285: invokespecial #244                // Method net/minecraft/item/ItemStack."<init>":(Lnet/minecraft/item/Item;II)V
     288: areturn
     289: new           #172                // class net/minecraft/item/ItemStack
     292: dup
     293: getstatic     #262                // Field com/pam/harvestcraft/item/ItemRegistry.clamrawItem:Lnet/minecraft/item/Item;
     296: iconst_1
     297: iconst_0
     298: invokespecial #244                // Method net/minecraft/item/ItemStack."<init>":(Lnet/minecraft/item/Item;II)V
     301: areturn
     302: new           #172                // class net/minecraft/item/ItemStack
     305: dup
     306: getstatic     #265                // Field com/pam/harvestcraft/item/ItemRegistry.crabrawItem:Lnet/minecraft/item/Item;
     309: iconst_1
     310: iconst_0
     311: invokespecial #244                // Method net/minecraft/item/ItemStack."<init>":(Lnet/minecraft/item/Item;II)V
     314: areturn
     315: new           #172                // class net/minecraft/item/ItemStack
     318: dup
     319: getstatic     #268                // Field com/pam/harvestcraft/item/ItemRegistry.crayfishrawItem:Lnet/minecraft/item/Item;
     322: iconst_1
     323: iconst_0
     324: invokespecial #244                // Method net/minecraft/item/ItemStack."<init>":(Lnet/minecraft/item/Item;II)V
     327: areturn
     328: new           #172                // class net/minecraft/item/ItemStack
     331: dup
     332: getstatic     #271                // Field com/pam/harvestcraft/item/ItemRegistry.eelrawItem:Lnet/minecraft/item/Item;
     335: iconst_1
     336: iconst_0
     337: invokespecial #244                // Method net/minecraft/item/ItemStack."<init>":(Lnet/minecraft/item/Item;II)V
     340: areturn
     341: new           #172                // class net/minecraft/item/ItemStack
     344: dup
     345: getstatic     #274                // Field com/pam/harvestcraft/item/ItemRegistry.frograwItem:Lnet/minecraft/item/Item;
     348: iconst_1
     349: iconst_0
     350: invokespecial #244                // Method net/minecraft/item/ItemStack."<init>":(Lnet/minecraft/item/Item;II)V
     353: areturn
     354: new           #172                // class net/minecraft/item/ItemStack
     357: dup
     358: getstatic     #277                // Field com/pam/harvestcraft/item/ItemRegistry.grouperrawItem:Lnet/minecraft/item/Item;
     361: iconst_1
     362: iconst_0
     363: invokespecial #244                // Method net/minecraft/item/ItemStack."<init>":(Lnet/minecraft/item/Item;II)V
     366: areturn
     367: new           #172                // class net/minecraft/item/ItemStack
     370: dup
     371: getstatic     #280                // Field com/pam/harvestcraft/item/ItemRegistry.herringrawItem:Lnet/minecraft/item/Item;
     374: iconst_1
     375: iconst_0
     376: invokespecial #244                // Method net/minecraft/item/ItemStack."<init>":(Lnet/minecraft/item/Item;II)V
     379: areturn
     380: new           #172                // class net/minecraft/item/ItemStack
     383: dup
     384: getstatic     #283                // Field com/pam/harvestcraft/item/ItemRegistry.jellyfishrawItem:Lnet/minecraft/item/Item;
     387: iconst_1
     388: iconst_0
     389: invokespecial #244                // Method net/minecraft/item/ItemStack."<init>":(Lnet/minecraft/item/Item;II)V
     392: areturn
     393: new           #172                // class net/minecraft/item/ItemStack
     396: dup
     397: getstatic     #286                // Field com/pam/harvestcraft/item/ItemRegistry.mudfishrawItem:Lnet/minecraft/item/Item;
     400: iconst_1
     401: iconst_0
     402: invokespecial #244                // Method net/minecraft/item/ItemStack."<init>":(Lnet/minecraft/item/Item;II)V
     405: areturn
     406: new           #172                // class net/minecraft/item/ItemStack
     409: dup
     410: getstatic     #289                // Field com/pam/harvestcraft/item/ItemRegistry.octopusrawItem:Lnet/minecraft/item/Item;
     413: iconst_1
     414: iconst_0
     415: invokespecial #244                // Method net/minecraft/item/ItemStack."<init>":(Lnet/minecraft/item/Item;II)V
     418: areturn
     419: new           #172                // class net/minecraft/item/ItemStack
     422: dup
     423: getstatic     #292                // Field com/pam/harvestcraft/item/ItemRegistry.perchrawItem:Lnet/minecraft/item/Item;
     426: iconst_1
     427: iconst_0
     428: invokespecial #244                // Method net/minecraft/item/ItemStack."<init>":(Lnet/minecraft/item/Item;II)V
     431: areturn
     432: new           #172                // class net/minecraft/item/ItemStack
     435: dup
     436: getstatic     #295                // Field com/pam/harvestcraft/item/ItemRegistry.scalloprawItem:Lnet/minecraft/item/Item;
     439: iconst_1
     440: iconst_0
     441: invokespecial #244                // Method net/minecraft/item/ItemStack."<init>":(Lnet/minecraft/item/Item;II)V
     444: areturn
     445: new           #172                // class net/minecraft/item/ItemStack
     448: dup
     449: getstatic     #298                // Field com/pam/harvestcraft/item/ItemRegistry.shrimprawItem:Lnet/minecraft/item/Item;
     452: iconst_1
     453: iconst_0
     454: invokespecial #244                // Method net/minecraft/item/ItemStack."<init>":(Lnet/minecraft/item/Item;II)V
     457: areturn
     458: new           #172                // class net/minecraft/item/ItemStack
     461: dup
     462: getstatic     #301                // Field com/pam/harvestcraft/item/ItemRegistry.snailrawItem:Lnet/minecraft/item/Item;
     465: iconst_1
     466: iconst_0
     467: invokespecial #244                // Method net/minecraft/item/ItemStack."<init>":(Lnet/minecraft/item/Item;II)V
     470: areturn
     471: new           #172                // class net/minecraft/item/ItemStack
     474: dup
     475: getstatic     #304                // Field com/pam/harvestcraft/item/ItemRegistry.snapperrawItem:Lnet/minecraft/item/Item;
     478: iconst_1
     479: iconst_0
     480: invokespecial #244                // Method net/minecraft/item/ItemStack."<init>":(Lnet/minecraft/item/Item;II)V
     483: areturn
     484: new           #172                // class net/minecraft/item/ItemStack
     487: dup
     488: getstatic     #307                // Field com/pam/harvestcraft/item/ItemRegistry.tilapiarawItem:Lnet/minecraft/item/Item;
     491: iconst_1
     492: iconst_0
     493: invokespecial #244                // Method net/minecraft/item/ItemStack."<init>":(Lnet/minecraft/item/Item;II)V
     496: areturn
     497: new           #172                // class net/minecraft/item/ItemStack
     500: dup
     501: getstatic     #310                // Field com/pam/harvestcraft/item/ItemRegistry.troutrawItem:Lnet/minecraft/item/Item;
     504: iconst_1
     505: iconst_0
     506: invokespecial #244                // Method net/minecraft/item/ItemStack."<init>":(Lnet/minecraft/item/Item;II)V
     509: areturn
     510: new           #172                // class net/minecraft/item/ItemStack
     513: dup
     514: getstatic     #313                // Field com/pam/harvestcraft/item/ItemRegistry.tunarawItem:Lnet/minecraft/item/Item;
     517: iconst_1
     518: iconst_0
     519: invokespecial #244                // Method net/minecraft/item/ItemStack."<init>":(Lnet/minecraft/item/Item;II)V
     522: areturn
     523: new           #172                // class net/minecraft/item/ItemStack
     526: dup
     527: getstatic     #316                // Field com/pam/harvestcraft/item/ItemRegistry.turtlerawItem:Lnet/minecraft/item/Item;
     530: iconst_1
     531: iconst_0
     532: invokespecial #244                // Method net/minecraft/item/ItemStack."<init>":(Lnet/minecraft/item/Item;II)V
     535: areturn
     536: new           #172                // class net/minecraft/item/ItemStack
     539: dup
     540: getstatic     #319                // Field com/pam/harvestcraft/item/ItemRegistry.walleyerawItem:Lnet/minecraft/item/Item;
     543: iconst_1
     544: iconst_0
     545: invokespecial #244                // Method net/minecraft/item/ItemStack."<init>":(Lnet/minecraft/item/Item;II)V
     548: areturn
     549: new           #172                // class net/minecraft/item/ItemStack
     552: dup
     553: getstatic     #241                // Field net/minecraft/init/Items.FISH:Lnet/minecraft/item/Item;
     556: iconst_1
     557: iconst_0
     558: invokespecial #244                // Method net/minecraft/item/ItemStack."<init>":(Lnet/minecraft/item/Item;II)V
     561: areturn
     562: new           #172                // class net/minecraft/item/ItemStack
     565: dup
     566: getstatic     #241                // Field net/minecraft/init/Items.FISH:Lnet/minecraft/item/Item;
     569: iconst_1
     570: iconst_0
     571: invokespecial #244                // Method net/minecraft/item/ItemStack."<init>":(Lnet/minecraft/item/Item;II)V
     574: areturn
     575: new           #172                // class net/minecraft/item/ItemStack
     578: dup
     579: getstatic     #322                // Field com/pam/harvestcraft/item/ItemRegistry.greenheartfishItem:Lnet/minecraft/item/Item;
     582: iconst_1
     583: iconst_0
     584: invokespecial #244                // Method net/minecraft/item/ItemStack."<init>":(Lnet/minecraft/item/Item;II)V
     587: areturn
     588: aconst_null
     589: areturn

  public net.minecraft.util.text.ITextComponent getDisplayName();
    Code:
       0: aconst_null
       1: areturn

  public net.minecraft.network.play.server.SPacketUpdateTileEntity getUpdatePacket();
    Code:
       0: new           #65                 // class net/minecraft/nbt/NBTTagCompound
       3: dup
       4: invokespecial #348                // Method net/minecraft/nbt/NBTTagCompound."<init>":()V
       7: astore_1
       8: aload_0
       9: aload_1
      10: invokevirtual #349                // Method writeToNBT:(Lnet/minecraft/nbt/NBTTagCompound;)Lnet/minecraft/nbt/NBTTagCompound;
      13: pop
      14: new           #351                // class net/minecraft/network/play/server/SPacketUpdateTileEntity
      17: dup
      18: aload_0
      19: invokevirtual #196                // Method getPos:()Lnet/minecraft/util/math/BlockPos;
      22: iconst_1
      23: aload_1
      24: invokespecial #354                // Method net/minecraft/network/play/server/SPacketUpdateTileEntity."<init>":(Lnet/minecraft/util/math/BlockPos;ILnet/minecraft/nbt/NBTTagCompound;)V
      27: areturn

  public void onDataPacket(net.minecraft.network.NetworkManager, net.minecraft.network.play.server.SPacketUpdateTileEntity);
    Code:
       0: aload_0
       1: aload_2
       2: invokevirtual #360                // Method net/minecraft/network/play/server/SPacketUpdateTileEntity.getNbtCompound:()Lnet/minecraft/nbt/NBTTagCompound;
       5: invokevirtual #361                // Method readFromNBT:(Lnet/minecraft/nbt/NBTTagCompound;)V
       8: return

  public boolean canInteractWith(net.minecraft.entity.player.EntityPlayer);
    Code:
       0: aload_0
       1: invokevirtual #370                // Method isInvalid:()Z
       4: ifne          38
       7: aload_1
       8: aload_0
       9: getfield      #113                // Field pos:Lnet/minecraft/util/math/BlockPos;
      12: ldc2_w        #371                // double 0.5d
      15: ldc2_w        #371                // double 0.5d
      18: ldc2_w        #371                // double 0.5d
      21: invokevirtual #376                // Method net/minecraft/util/math/BlockPos.add:(DDD)Lnet/minecraft/util/math/BlockPos;
      24: invokevirtual #382                // Method net/minecraft/entity/player/EntityPlayer.getDistanceSq:(Lnet/minecraft/util/math/BlockPos;)D
      27: ldc2_w        #383                // double 64.0d
      30: dcmpg
      31: ifgt          38
      34: iconst_1
      35: goto          39
      38: iconst_0
      39: ireturn

  public java.lang.String getGuiID();
    Code:
       0: ldc_w         #390                // String harvestcraft:watertrap
       3: areturn
}
